oci_openai/__about__.py
oci_openai/__init__.py
oci_openai/oci_openai.py
oci_openai-1.0.0.dist-info/METADATA
oci_openai-1.0.0.dist-info/WHEEL
oci_openai-1.0.0.dist-info/licenses/LICENSE.txt
oci_openai-1.0.0.dist-info/RECORD
