Metadata-Version: 2.4
Name: oci-openai
Version: 1.0.0
Summary: OCI authentication and authorization utilities for OpenAI python SDK
Project-URL: Documentation, https://github.com/oracle-samples/oci-openai#readme
Project-URL: Issues, https://github.com/oracle-samples/oci-openai/issues
Project-URL: Source, https://github.com/oracle-samples/oci-openai
Author-email: Chao Yang <chao.c.yang@oracle.com>
License-Expression: UPL-1.0
License-File: LICENSE.txt
Keywords: AI,Artificial Intelligence,GenAI,Generative AI,OCI,Oracle,Oracle Cloud Infrastructure
Classifier: Intended Audience :: Developers
Classifier: Programming Language :: Python
Classifier: Programming Language :: Python :: 3.9
Classifier: Programming Language :: Python :: 3.10
Classifier: Programming Language :: Python :: 3.11
Classifier: Programming Language :: Python :: 3.12
Classifier: Topic :: Software Development :: Libraries :: Python Modules
Classifier: Topic :: System :: Benchmark
Classifier: Typing :: Typed
Requires-Python: >=3.9
Requires-Dist: httpx<1,>=0.23.0
Requires-Dist: oci>=2.150.1
Requires-Dist: openai>=v1.108.1
Requires-Dist: requests<3.0.0,>=2.32.1
Provides-Extra: dev
Requires-Dist: ag2[openai]; extra == 'dev'
Requires-Dist: black<25.0.0,>=24.8.0; extra == 'dev'
Requires-Dist: isort<6.0.0,>=5.13.2; extra == 'dev'
Requires-Dist: mypy<2.0.0,>=1.11.1; extra == 'dev'
Requires-Dist: openai-agents>=0.5.1; extra == 'dev'
Requires-Dist: pytest-asyncio; extra == 'dev'
Requires-Dist: pytest-cov<6.0.0,>=5.0.0; extra == 'dev'
Requires-Dist: pytest-httpx; extra == 'dev'
Requires-Dist: pytest-mock; extra == 'dev'
Requires-Dist: pytest<9.0.0,>=8.3.2; extra == 'dev'
Requires-Dist: respx; extra == 'dev'
Requires-Dist: ruff<0.6.0,>=0.5.6; extra == 'dev'
Requires-Dist: typing-extensions<5,>=4.11; extra == 'dev'
